rich_structlog/__init__.py
rich_structlog/log.py
rich_structlog/py.typed
rich_structlog-0.4.1.dist-info/METADATA
rich_structlog-0.4.1.dist-info/WHEEL
rich_structlog-0.4.1.dist-info/licenses/LICENSE
rich_structlog-0.4.1.dist-info/RECORD
