Metadata-Version: 2.3
Name: rich-structlog
Version: 0.4.1
Summary: Add your description here
Author-email: Khaled Sakallah <ks.dev@posteo.de>
License: MIT
License-File: LICENSE
Requires-Python: >=3.10
Requires-Dist: colorama>=0.4.6
Requires-Dist: rich>=13.9.2
Requires-Dist: structlog>=24.4.0
